washing_machine.v
module washing_machine(clk, reset, door_close, start, filled, detergent_added, cycle_timeout, drained, spin_timeout, door_lock, motor_on, fill_value_on, drain_value_on, done, soap_wash, water_wash);

	input clk, reset, door_close, start, filled, detergent_added, cycle_timeout, drained, spin_timeout;
	output reg door_lock, motor_on, fill_value_on, drain_value_on, done, soap_wash, water_wash; 
	
	//defining the states
	parameter check_door = 3'b000;
	parameter fill_water = 3'b001;
	parameter add_detergent = 3'b010;
	parameter cycle = 3'b011;
	parameter drain_water = 3'b100;
	parameter spin = 3'b101;
	
	reg[2:0] current_state, next_state;
	
	always@(current_state or start or door_close or filled or detergent_added or drained or cycle_timeout or spin_timeout)
	begin
	case(current_state)
		check_door:
			if(start==1 && door_close==1)
			begin
				next_state = fill_water;
				motor_on = 0;
				fill_value_on = 0;
				drain_value_on = 0;
				door_lock = 1;
				soap_wash = 0;
				water_wash = 0;
				done = 0;
			end
			else
			begin
				next_state = current_state;
				motor_on = 0;
				fill_value_on = 0;
				drain_value_on = 0;
				door_lock = 0;
				soap_wash = 0;
				water_wash = 0;
				done = 0;
			end
			
			fill_water:
			if (filled==1)
			begin
				if(soap_wash == 0)
				begin
					next_state = add_detergent;
					motor_on = 0;
					fill_value_on = 0;
					drain_value_on = 0;
					door_lock = 1;
					soap_wash = 1;
					water_wash = 0;
					done = 0;
				end
				else
				begin
					next_state = cycle;
					motor_on = 0;
					fill_value_on = 0;
					drain_value_on = 0;
					door_lock = 1;
					soap_wash = 1;
					water_wash = 1;
					done = 0;
				end
			end
			else
			begin
				next_state = current_state;
				motor_on = 0;
				fill_value_on = 1;
				drain_value_on = 0;
				door_lock = 1;
				done = 0;
			end
			add_detergent:
			if(detergent_added==1)
			begin
				next_state = cycle;
				motor_on = 0;
				fill_value_on = 0;
				drain_value_on = 0;
				door_lock = 1;
				soap_wash = 1;
				done = 0;
			end
			else
			begin
				next_state = current_state;
				motor_on = 0;
				fill_value_on = 0;
				drain_value_on = 0;
				door_lock = 1;
				soap_wash = 1;
				water_wash = 0;
				done = 0;
			end
			cycle:
			if(cycle_timeout == 1)
			begin
				next_state = drain_water;
				motor_on = 0;
				fill_value_on = 0;
				drain_value_on = 0;
				door_lock = 1;
				//soap_wash = 1;
				done = 0;
			end
			else
			begin
				next_state = current_state;
				motor_on = 1;
				fill_value_on = 0;
				drain_value_on = 0;
				door_lock = 1;
				//soap_wash = 1;
				done = 0;
			end
			drain_water:
			 if(drained==1)
			 begin
				if(water_wash==0)
				begin
					next_state = fill_water;
					motor_on = 0;
					fill_value_on = 0;
					drain_value_on = 0;
					door_lock = 1;
					soap_wash = 1;
					//water_wash = 1;
					done = 0;
				end
				else
				begin
				next_state = spin;
					motor_on = 0;
					fill_value_on = 0;
					drain_value_on = 0;
					door_lock = 1;
					soap_wash = 1;
					water_wash = 1;
					done = 0;
				end
			end
			else
			begin
				next_state = current_state;
				motor_on = 0;
				fill_value_on = 0;
				drain_value_on = 1;
				door_lock = 1;
				soap_wash = 1;
				//water_wash = 1;
				done = 0;
			end
			spin:
			if(spin_timeout==1)
			begin
				next_state = door_close;
				motor_on = 0;
				fill_value_on = 0;
				drain_value_on = 0;
				door_lock = 1;
				soap_wash = 1;
				water_wash = 1;
				done = 1;
			end
			else
			begin
				next_state = current_state;
				motor_on = 0;
				fill_value_on = 0;
				drain_value_on = 1;
				door_lock = 1;
				soap_wash = 1;
				water_wash = 1;
				done = 0;
			end
			default:
				next_state = check_door;
				
			endcase
	end
	
	always@(posedge clk or negedge reset)
	begin
		if(reset)
		begin
			current_state<=3'b000;
		end
		else
		begin
			current_state<=next_state;
		end
	end
	
endmodule

washing_machine_tb.v
`timescale 10ns/1ns
`include "washing_machine.v"

module washing_machine_tb();
    reg clk, reset, door_close, start, filled, detergent_added, cycle_timeout, drained, spin_timeout;
    wire door_lock, motor_on, fill_value_on, drain_value_on, done, soap_wash, water_wash; 
    
    // Instantiate the washing machine module
    washing_machine machine1 (
        .clk(clk), 
        .reset(reset), 
        .door_close(door_close), 
        .start(start), 
        .filled(filled), 
        .detergent_added(detergent_added), 
        .cycle_timeout(cycle_timeout), 
        .drained(drained), 
        .spin_timeout(spin_timeout), 
        .door_lock(door_lock), 
        .motor_on(motor_on), 
        .fill_value_on(fill_value_on), 
        .drain_value_on(drain_value_on), 
        .done(done), 
        .soap_wash(soap_wash), 
        .water_wash(water_wash)
    );

    initial begin
        $dumpfile("washing_machine_data.vcd");
        $dumpvars(0, washing_machine_tb);  // Correct module name used
    end

    initial begin
        clk = 0;
        reset = 1;
        start = 0;
        door_close = 0;
        filled = 0;
        drained = 0;
        detergent_added = 0;
        cycle_timeout = 0;
        spin_timeout = 0;
        
        #5 reset = 0;
        #5 start = 1; door_close = 1;
        #10 filled = 1;
        #10 detergent_added = 1;
        //filled = 0;
        #10 cycle_timeout = 1;
        //detergent_added = 0;
        #10 drained = 1;
        //cycle_timeout = 0;
        #10 spin_timeout = 1;
        //drained = 0;
    end
    
    always begin
        #5 clk = ~clk;
    end
    
    initial begin
        $display("Clock=%b, Reset=%b, start=%b, door_close=%b, filled=%b, detergent_added=%b, cycle_timeout=%b, drained=%b, spin_timeout=%b, door_lock=%b, motor_on=%b, fill_valve_on=%b, drain_valve_on=%b, soap_wash=%b, water_wash=%b, done=%b", clk, reset, start, door_close, filled, detergent_added, cycle_timeout, drained, spin_timeout, door_lock, motor_on, fill_value_on, drain_value_on, soap_wash, water_wash, done);
     #200 $finish;   
    end
endmodule

washing_data.vcd
$date
	Wed Jun 26 15:55:07 2024
$end
$version
	Icarus Verilog
$end
$timescale
	1ns
$end
$scope module washing_machine_tb $end
$var wire 1 ! water_wash $end
$var wire 1 " soap_wash $end
$var wire 1 # motor_on $end
$var wire 1 $ fill_value_on $end
$var wire 1 % drain_value_on $end
$var wire 1 & door_lock $end
$var wire 1 ' done $end
$var reg 1 ( clk $end
$var reg 1 ) cycle_timeout $end
$var reg 1 * detergent_added $end
$var reg 1 + door_close $end
$var reg 1 , drained $end
$var reg 1 - filled $end
$var reg 1 . reset $end
$var reg 1 / spin_timeout $end
$var reg 1 0 start $end
$scope module machine1 $end
$var wire 1 ( clk $end
$var wire 1 ) cycle_timeout $end
$var wire 1 * detergent_added $end
$var wire 1 + door_close $end
$var wire 1 , drained $end
$var wire 1 - filled $end
$var wire 1 . reset $end
$var wire 1 / spin_timeout $end
$var wire 1 0 start $end
$var parameter 3 1 add_detergent $end
$var parameter 3 2 check_door $end
$var parameter 3 3 cycle $end
$var parameter 3 4 drain_water $end
$var parameter 3 5 fill_water $end
$var parameter 3 6 spin $end
$var reg 3 7 current_state [2:0] $end
$var reg 1 ' done $end
$var reg 1 & door_lock $end
$var reg 1 % drain_value_on $end
$var reg 1 $ fill_value_on $end
$var reg 1 # motor_on $end
$var reg 3 8 next_state [2:0] $end
$var reg 1 " soap_wash $end
$var reg 1 ! water_wash $end
$upscope $end
$upscope $end
$enddefinitions $end
$comment Show the parameter values. $end
$dumpall
b101 6
b1 5
b100 4
b11 3
b0 2
b10 1
$end
#0
$dumpvars
b0 8
bx 7
00
0/
1.
0-
0,
0+
0*
0)
0(
x'
x&
x%
x$
x#
x"
x!
$end
#50
0'
0!
0"
0&
0%
0$
0#
b0 7
1(
0.
#100
1&
b1 8
0(
1+
10
#150
1$
b1 7
1(
#200
1"
0$
b10 8
0(
1-
#250
b10 7
1(
#300
b11 8
0(
1*
#350
1#
b11 7
1(
#400
0#
b100 8
0(
1)
#450
1%
b100 7
1(
#500
0%
b1 8
0(
1,
#550
1!
b11 8
b1 7
1(
#600
0(
1/
#650
b100 8
b11 7
1(
#700
0(
#750
b101 8
b100 7
1(
#800
0(
#850
1'
b1 8
b101 7
1(
#900
0(
#950
0'
b11 8
b1 7
1(
#1000
0(
#1050
b100 8
b11 7
1(
#1100
0(
#1150
b101 8
b100 7
1(
#1200
0(
#1250
1'
b1 8
b101 7
1(
#1300
0(
#1350
0'
b11 8
b1 7
1(
#1400
0(
#1450
b100 8
b11 7
1(
#1500
0(
#1550
b101 8
b100 7
1(
#1600
0(
#1650
1'
b1 8
b101 7
1(
#1700
0(
#1750
0'
b11 8
b1 7
1(
#1800
0(
#1850
b100 8
b11 7
1(
#1900
0(
#1950
b101 8
b100 7
1(
